README.md
setup.py
TenHelloWorlds/GoodByeWorlds.py
TenHelloWorlds/HelloWorlds.py
TenHelloWorlds/__init__.py
TenHelloWorlds.egg-info/PKG-INFO
TenHelloWorlds.egg-info/SOURCES.txt
TenHelloWorlds.egg-info/dependency_links.txt
TenHelloWorlds.egg-info/top_level.txt