Metadata-Version: 1.0
Name: TenHelloWorlds
Version: 1
Summary: Learing to create python packages
Home-page: https://github.com/BlonskiP/TenHelloWorlds
Author: Piotr Blonski
Author-email: piotrblonski96@gmail.com
License: MIT
Platform: UNKNOWN
